lsst/ctrl/bps/panda/__init__.py
lsst/ctrl/bps/panda/cmd_line_embedder.py
lsst/ctrl/bps/panda/constants.py
lsst/ctrl/bps/panda/panda_auth_drivers.py
lsst/ctrl/bps/panda/panda_auth_utils.py
lsst/ctrl/bps/panda/panda_exceptions.py
lsst/ctrl/bps/panda/panda_service.py
lsst/ctrl/bps/panda/utils.py
lsst/ctrl/bps/panda/version.py
lsst/ctrl/bps/panda/cli/__init__.py
lsst/ctrl/bps/panda/cli/panda_auth.py
lsst/ctrl/bps/panda/cli/cmd/__init__.py
lsst/ctrl/bps/panda/cli/cmd/panda_auth_commands.py
lsst/ctrl/bps/panda/conf_example/example_panda_SLAC.yaml
lsst/ctrl/bps/panda/conf_example/pipelines_check_idf.yaml
lsst/ctrl/bps/panda/conf_example/test_idf.yaml
lsst/ctrl/bps/panda/conf_example/test_sdf.yaml
lsst/ctrl/bps/panda/conf_example/test_usdf.yaml
lsst/ctrl/bps/panda/edgenode/__init__.py
lsst/ctrl/bps/panda/edgenode/build_cmd_line_decoder.py
lsst/ctrl/bps/panda/edgenode/cmd_line_decoder.py
lsst_ctrl_bps_panda-30.0.0.dist-info/licenses/COPYRIGHT
lsst_ctrl_bps_panda-30.0.0.dist-info/licenses/LICENSE
lsst_ctrl_bps_panda-30.0.0.dist-info/licenses/bsd_license.txt
lsst_ctrl_bps_panda-30.0.0.dist-info/licenses/gpl-v3.0.txt
lsst_ctrl_bps_panda-30.0.0.dist-info/METADATA
lsst_ctrl_bps_panda-30.0.0.dist-info/WHEEL
lsst_ctrl_bps_panda-30.0.0.dist-info/top_level.txt
lsst_ctrl_bps_panda-30.0.0.dist-info/zip-safe
lsst_ctrl_bps_panda-30.0.0.dist-info/RECORD
