Metadata-Version: 2.4
Name: lsst-ctrl-bps-panda
Version: 30.0.0
Summary: PanDA plugin for lsst-ctrl-bps.
Author-email: Rubin Observatory Data Management <dm-admin@lists.lsst.org>
License-Expression: BSD-3-Clause OR GPL-3.0-or-later
Project-URL: Homepage, https://github.com/lsst/ctrl_bps_panda
Keywords: lsst
Classifier: Intended Audience :: Science/Research
Classifier: Operating System :: OS Independent
Classifier: Programming Language :: Python :: 3
Classifier: Programming Language :: Python :: 3.11
Classifier: Programming Language :: Python :: 3.12
Classifier: Programming Language :: Python :: 3.13
Classifier: Programming Language :: Python :: 3.14
Classifier: Topic :: Scientific/Engineering :: Astronomy
Requires-Python: >=3.11.0
License-File: COPYRIGHT
License-File: LICENSE
License-File: bsd_license.txt
License-File: gpl-v3.0.txt
Requires-Dist: click>=7.0
Requires-Dist: pyyaml>=5.1
Requires-Dist: idds-client
Requires-Dist: idds-common
Requires-Dist: idds-doma
Requires-Dist: idds-workflow
Requires-Dist: panda-client
Requires-Dist: lsst-ctrl-bps
Requires-Dist: lsst-daf-butler
Requires-Dist: lsst-resources
Requires-Dist: lsst-utils
Provides-Extra: test
Requires-Dist: pytest>=3.2; extra == "test"
Requires-Dist: pytest-openfiles>=0.5.0; extra == "test"
Dynamic: license-file
